xscanner/__init__.py
xscanner/cli.py
xscanner/core.py
xscanner/grammar/RuleLexer.interp
xscanner/grammar/RuleLexer.py
xscanner/grammar/RuleLexer.tokens
xscanner/grammar/RuleParser.interp
xscanner/grammar/RuleParser.py
xscanner/grammar/RuleParser.tokens
xscanner/grammar/RuleParserVisitor.py
xscanner/grammar/__init__.py
xscanner/grammar/visitor.py
xscanner/modules/__init__.py
xscanner/modules/zip.py
xscanner-0.2.0.dist-info/entry_points.txt
xscanner-0.2.0.dist-info/LICENSE
xscanner-0.2.0.dist-info/WHEEL
xscanner-0.2.0.dist-info/METADATA
xscanner-0.2.0.dist-info/RECORD
